scpevn/__init__.py
scpevn/app.py
scpevn-1.0.0.dist-info/LICENSE
scpevn-1.0.0.dist-info/METADATA
scpevn-1.0.0.dist-info/WHEEL
scpevn-1.0.0.dist-info/top_level.txt
scpevn-1.0.0.dist-info/RECORD
