Metadata-Version: 2.1
Name: scpevn
Version: 1.0.0
Summary: https://vnhass.blogspot.com/
Home-page: https://github.com/pypa/sampleproject
Author: @trumxuquang
Author-email: trumxuquang@gmail.com
Classifier: Programming Language :: Python :: 3
Classifier: Programming Language :: Python :: 3.6
Classifier: Programming Language :: Python :: 3.7
Classifier: Programming Language :: Python :: 3.8
Classifier: Programming Language :: Python :: 3.9
Classifier: Programming Language :: Python :: 3.10
Classifier: Programming Language :: Python :: 3 :: Only
License-File: LICENSE
